crx_analyzer/__init__.py
crx_analyzer/cli.py
crx_analyzer/download.py
crx_analyzer/extension.py
crx_analyzer/models.py
crx_analyzer/risk.py
crx_analyzer-0.3.0.dist-info/METADATA
crx_analyzer-0.3.0.dist-info/WHEEL
crx_analyzer-0.3.0.dist-info/entry_points.txt
crx_analyzer-0.3.0.dist-info/licenses/LICENSE.txt
crx_analyzer-0.3.0.dist-info/RECORD
