Metadata-Version: 2.4
Name: crx-analyzer
Version: 0.3.0
Summary: Add your description here
License-File: LICENSE.txt
Requires-Python: >=3.10
Requires-Dist: click>=8.1.8
Requires-Dist: pydantic>=2.10.5
Requires-Dist: requests>=2.32.3
Requires-Dist: rich>=13.9.4
